[
   {
      "skillUIID":0,
      "lev0_skillDescription":"효과 지속시간 +10%",
      "lev1_skillDescription":"효과 지속시간 +20%",
      "lev2_skillDescription":"효과 지속시간 +30%",
      "lev3_skillDescription":"효과 지속시간 +40%",
      "lev4_skillDescription":"효과 지속시간 +50%",
      "lev5_skillDescription":"",
      "skillName_A":"외골격 갑옷",
      "skillName_B":""
   },
   {
      "skillUIID":1,
      "lev0_skillDescription":"공격력 +10%",
      "lev1_skillDescription":"공격력 +20%",
      "lev2_skillDescription":"공격력 +30%",
      "lev3_skillDescription":"공격력 +40%",
      "lev4_skillDescription":"공격력 +50%",
      "lev5_skillDescription":"",
      "skillName_A":"고화력 총알",
      "skillName_B":""
   },
   {
      "skillUIID":2,
      "lev0_skillDescription":"Exp 획득 +8%",
      "lev1_skillDescription":"Exp 획득 +16%",
      "lev2_skillDescription":"Exp 획득 +24%",
      "lev3_skillDescription":"Exp 획득 +32%",
      "lev4_skillDescription":"Exp 획득 +40%",
      "lev5_skillDescription":"",
      "skillName_A":"닌자 스크롤",
      "skillName_B":""
   },
   {
      "skillUIID":3,
      "lev0_skillDescription":"받는 피해량 감소 -10%",
      "lev1_skillDescription":"받는 피해량 감소 -20%",
      "lev2_skillDescription":"받는 피해량 감소 -30%",
      "lev3_skillDescription":"받는 피해량 감소 -40%",
      "lev4_skillDescription":"받는 피해량 감소 -50%",
      "lev5_skillDescription":"",
      "skillName_A":"부랑자의 갑옷",
      "skillName_B":""
   },
   {
      "skillUIID":4,
      "lev0_skillDescription":"5초마다 Hp 1%회복",
      "lev1_skillDescription":"5초마다 Hp 2%회복",
      "lev2_skillDescription":"5초마다 Hp 3%회복",
      "lev3_skillDescription":"5초마다 Hp 4%회복",
      "lev4_skillDescription":"5초마다 Hp 5%회복",
      "lev5_skillDescription":"",
      "skillName_A":"에너지 드링크",
      "skillName_B":""
   },
   {
      "skillUIID":5,
      "lev0_skillDescription":"모든 공격 시간 간격 -8%",
      "lev1_skillDescription":"모든 공격 시간 간격 -16%",
      "lev2_skillDescription":"모든 공격 시간 간격 -24%",
      "lev3_skillDescription":"모든 공격 시간 간격 -32%",
      "lev4_skillDescription":"모든 공격 시간 간격 -40%",
      "lev5_skillDescription":"",
      "skillName_A":"에너지 큐브",
      "skillName_B":""
   },
   {
      "skillUIID":6,
      "lev0_skillDescription":"골드획득 +8%",
      "lev1_skillDescription":"골드획득 +16%",
      "lev2_skillDescription":"골드획득 +824%",
      "lev3_skillDescription":"골드획득 +32%",
      "lev4_skillDescription":"골드획득 +40%",
      "lev5_skillDescription":"",
      "skillName_A":"석유채",
      "skillName_B":""
   },
   {
      "skillUIID":7,
      "lev0_skillDescription":"탄약과 무기속도 +10%",
      "lev1_skillDescription":"탄약과 무기속도 +20%",
      "lev2_skillDescription":"탄약과 무기속도 +30%",
      "lev3_skillDescription":"탄약과 무기속도 +40%",
      "lev4_skillDescription":"탄약과 무기속도 +50%",
      "lev5_skillDescription":"",
      "skillName_A":"탄약 추진기",
      "skillName_B":""
   },
   {
      "skillUIID":8,
      "lev0_skillDescription":"이동 속도 +10%",
      "lev1_skillDescription":"이동 속도 +20%",
      "lev2_skillDescription":"이동 속도 +30%",
      "lev3_skillDescription":"이동 속도 +40%",
      "lev4_skillDescription":"이동 속도 +50%",
      "lev5_skillDescription":"",
      "skillName_A":"운동화",
      "skillName_B":""
   },
   {
      "skillUIID":9,
      "lev0_skillDescription":"아이템획득범위 +100%",
      "lev1_skillDescription":"아이템획득범위 +200%",
      "lev2_skillDescription":"아이템획득범위 +300%",
      "lev3_skillDescription":"아이템획득범위 +400%",
      "lev4_skillDescription":"아이템획득범위 +500%",
      "lev5_skillDescription":"",
      "skillName_A":"탄력 자석",
      "skillName_B":""
   },
   {
      "skillUIID":10,
      "lev0_skillDescription":"최대 Hp +20%",
      "lev1_skillDescription":"최대 Hp +40%",
      "lev2_skillDescription":"최대 Hp +60%",
      "lev3_skillDescription":"최대 Hp +80%",
      "lev4_skillDescription":"최대 Hp +100%",
      "lev5_skillDescription":"",
      "skillName_A":"피트니스 안내서",
      "skillName_B":""
   },
   {
      "skillUIID":11,
      "lev0_skillDescription":"모든 탄약 및 무기범위 +10%",
      "lev1_skillDescription":"모든 탄약 및 무기범위 +20%",
      "lev2_skillDescription":"모든 탄약 및 무기범위 +30%",
      "lev3_skillDescription":"모든 탄약 및 무기범위 +40%",
      "lev4_skillDescription":"모든 탄약 및 무기범위 +50%",
      "lev5_skillDescription":"",
      "skillName_A":"고성능 연료",
      "skillName_B":""
   },
   {
      "skillUIID":12,
      "lev0_skillDescription":"1개 투척. 총알 무효화",
      "lev1_skillDescription":"1개 추가",
      "lev2_skillDescription":"피해량 대폭 증가",
      "lev3_skillDescription":"크기 증가",
      "lev4_skillDescription":"크기 증가 및 피해량 증가",
      "lev5_skillDescription":"극성 반전",
      "skillName_A":"부메랑",
      "skillName_B":"마그네틱 다트"
   },
   {
      "skillUIID":13,
      "lev0_skillDescription":"1개 투척",
      "lev1_skillDescription":"1개 추가 및 피해량 증가",
      "lev2_skillDescription":"1개 추가 및 피해량 증가",
      "lev3_skillDescription":"1개 추가 및 피해량 증가",
      "lev4_skillDescription":"1개 추가 및 피해량 대폭 증가",
      "lev5_skillDescription":"세계 최강",
      "skillName_A":"벽돌",
      "skillName_B":"덤벨"
   },
  {
    "skillUIID": 14,
    "lev0_skillDescription": "1개 발사 ",
    "lev1_skillDescription": "1개 추가",
    "lev2_skillDescription": "1개 추가 및 비행속도 증가",
    "lev3_skillDescription": "1개 추가 및 비행속도 증가",
    "lev4_skillDescription": "1개 추가 및 데미지 증가",
    "lev5_skillDescription": "영원한 갈망",
    "skillName_A": "드릴샷",
    "skillName_B": "휘바람 화살"
  },
   {
      "skillUIID":15,
      "lev0_skillDescription":"드론 소환. 여러발의 미사일 발사 ",
      "lev1_skillDescription":"피해량 두배",
      "lev2_skillDescription":"미사일 개수 두배 ",
      "lev3_skillDescription":"피해량 대폭 증가 ",
      "lev4_skillDescription":"피해량 대폭 증가 ",
      "lev5_skillDescription":"하늘의 심판",
      "skillName_A":"A형 드론 ",
      "skillName_B":"파괴자"
   },
   {
      "skillUIID":16,
      "lev0_skillDescription":"B형 드론 소환. 여러발의 미사일 발사",
      "lev1_skillDescription":"미사일 개수 두배",
      "lev2_skillDescription":"미사일 개수 두배",
      "lev3_skillDescription":"피해량 대폭 증가",
      "lev4_skillDescription":"피해량 대폭 증가",
      "lev5_skillDescription":"하늘의 심판",
      "skillName_A":"B형 드론",
      "skillName_B":"파괴자"
   },
   {
      "skillUIID":17,
      "lev0_skillDescription":"두리안 1개 발사",
      "lev1_skillDescription":"피해량 두배 및 속도 증가",
      "lev2_skillDescription":"크기 증가",
      "lev3_skillDescription":"피해량 증가 및 속도 증가",
      "lev4_skillDescription":"크리 증가 및 피해량 두배",
      "lev5_skillDescription":"익은 과일은 향이 좋다",
      "skillName_A":"두리안",
      "skillName_B":"가시창"
   },
   {
      "skillUIID":18,
      "lev0_skillDescription":"팽이 2개 소환. 총알 무효화",
      "lev1_skillDescription":"팽이 1개 추가. 회전 속도 및 피해량 증가",
      "lev2_skillDescription":"팽이 1개 추가. 회전 속도 및 피해량 증가",
      "lev3_skillDescription":"팽이 1개 추가. 회전 속도 및 피해량 증가",
      "lev4_skillDescription":"팽이 1개 추가. 회전 속도 및 피해량 증가",
      "lev5_skillDescription":"죽음의 수레바퀴",
      "skillName_A":"수호자",
      "skillName_B":"수비자"
   },
   {
      "skillUIID":19,
      "lev0_skillDescription":"랜덤영역 한곳에 번개 공격",
      "lev1_skillDescription":"번개불 1개 추가 및 피해량 증가",
      "lev2_skillDescription":"번개불 1개 추가 및 피해량 증가",
      "lev3_skillDescription":"번개불 1개 추가 및 피해량 증가",
      "lev4_skillDescription":"번개불 1개 추가 및 피해량 증가",
      "lev5_skillDescription":"벼락같은 파괴",
      "skillName_A":"번개 발사기",
      "skillName_B":"천둥 배터리"
   },
   {
      "skillUIID":20,
      "lev0_skillDescription":"융해시키는 방어막을 생성",
      "lev1_skillDescription":"영역확대 및 피해량 증가",
      "lev2_skillDescription":"영역확대 및 피해량 증가",
      "lev3_skillDescription":"영역확대 및 피해량 증가",
      "lev4_skillDescription":"영역확대 및 피해량 증가",
      "lev5_skillDescription":"나의 영역",
      "skillName_A":"방어막",
      "skillName_B":"중력장"
   },
   {
      "skillUIID":21,
      "lev0_skillDescription":"화염병 2개 투척",
      "lev1_skillDescription":"1개 추가, 범위 증가, 피해량 증가",
      "lev2_skillDescription":"1개 추가, 범위 증가, 피해량 증가",
      "lev3_skillDescription":"1개 추가, 범위 증가, 피해량 증가",
      "lev4_skillDescription":"1개 추가, 범위 증가, 피해량 증가",
      "lev5_skillDescription":"초토화 정책",
      "skillName_A":"화염병",
      "skillName_B":"기름통"
   },
  {
    "skillUIID": 22,
    "lev0_skillDescription": "폭발성 로켓을 발사",
    "lev1_skillDescription": "로켓 피해량 두배",
    "lev2_skillDescription": "로켓 1개 추가",
    "lev3_skillDescription": "로켓 피해량 두배",
    "lev4_skillDescription": "로켓 1개 추가",
    "lev5_skillDescription": "식은 죽 먹기",
    "skillName_A": "로켓발사기",
    "skillName_B": "상어부리포"
  },
   {
      "skillUIID":23,
      "lev0_skillDescription":"튀는 축구공 1개 추가",
      "lev1_skillDescription":"1개 추가",
      "lev2_skillDescription":"비행속도 증가 및 피해량증가",
      "lev3_skillDescription":"비행속도 증가 및 피해량증가",
      "lev4_skillDescription":"1개 추가",
      "lev5_skillDescription":"양자 역학 난제",
      "skillName_A":"축구공",
      "skillName_B":"양자공"
   },
   {
      "skillUIID":24,
      "lev0_skillDescription":"블랙홀 데미지  증가",
      "lev1_skillDescription":"블랙홀 데미지  증가",
      "lev2_skillDescription":"블랙홀 크기 증가",
      "lev3_skillDescription":"블랙홀 데미지 증가",
      "lev4_skillDescription":"블랙홀 크기 및 데미지 증가",
      "lev5_skillDescription":"죽자하면 살 것이다",
      "skillName_A":"파괴의 힘",
      "skillName_B":"저승의 심판"
   },
   {
      "skillUIID":25,
      "lev0_skillDescription":"2x 피해량",
      "lev1_skillDescription":"2x 피해량",
      "lev2_skillDescription":"2x 피해량",
      "lev3_skillDescription":"2x 피해량",
      "lev4_skillDescription":"2x 피해량",
      "lev5_skillDescription":"결정적인 순간",
      "skillName_A":"리볼버",
      "skillName_B":"사신"
   },
   {
      "skillUIID":26,
      "lev0_skillDescription":"쿠나이 1개 추가. 피해량 증가 ",
      "lev1_skillDescription":"쿠나이 1개 추가. 피해량 증가 ",
      "lev2_skillDescription":"쿠나이 1개 추가. 피해량 증가 ",
      "lev3_skillDescription":"쿠나이 1개 추가. 피해량 증가 ",
      "lev4_skillDescription":"쿠나이 1개 추가. 피해량 증가 ",
      "lev5_skillDescription":"쥐도새도 모르게",
      "skillName_A":"쿠나이",
      "skillName_B":"유령 수리검"
   },
   {
      "skillUIID":27,
      "lev0_skillDescription":"검기회전 2회 ",
      "lev1_skillDescription":"검기 파워 증가. 검기회전 1회 증가",
      "lev2_skillDescription":"검기 파워 증가. 기공도 2회 증가",
      "lev3_skillDescription":"검기 파워 증가. 기공도 1회 증가",
      "lev4_skillDescription":"검기 파워 증가. ",
      "lev5_skillDescription":"전투 욕망",
      "skillName_A":"카타나",
      "skillName_B":"악마의 검 "
   },
   {
      "skillUIID":50,
      "lev0_skillDescription":"30% HP 회복",
      "lev1_skillDescription":"",
      "lev2_skillDescription":"",
      "lev3_skillDescription":"",
      "lev4_skillDescription":"",
      "lev5_skillDescription":"",
      "skillName_A":"햄 한 개",
      "skillName_B":""
   },
   {
      "skillUIID":51,
      "lev0_skillDescription":"50골드 획득",
      "lev1_skillDescription":"",
      "lev2_skillDescription":"",
      "lev3_skillDescription":"",
      "lev4_skillDescription":"",
      "lev5_skillDescription":"",
      "skillName_A":"골드 주머니",
      "skillName_B":""
   }
]